CHANGES.rst
LICENSE.txt
MANIFEST.in
README.rst
requirements.txt
requirements_dev.txt
setup.py
docs/api_reference.rst
docs/authors.rst
docs/changes.rst
docs/index.rst
docs/install.rst
docs/tutorial.rst
docs/upcoming.rst
docs/_build/html/_sources/api_reference.txt
docs/_build/html/_sources/authors.txt
docs/_build/html/_sources/changes.txt
docs/_build/html/_sources/index.txt
docs/_build/html/_sources/install.txt
docs/_build/html/_sources/tutorial.txt
docs/_build/html/_sources/upcoming.txt
linkGrabber/__init__.py
linkGrabber.egg-info/PKG-INFO
linkGrabber.egg-info/SOURCES.txt
linkGrabber.egg-info/dependency_links.txt
linkGrabber.egg-info/requires.txt
linkGrabber.egg-info/top_level.txt
linkGrabber/tests/__init__.py
linkGrabber/tests/test_data.py
linkGrabber/tests/test_scrape.py