Metadata-Version: 1.1
Name: linkGrabber
Version: 0.2.9
Summary: Scrape links from a single web page
Home-page: https://github.com/detroit-media-partnership/linkGrabber
Author: Eric Bower
Author-email: neurosnap@gmail.com
License: The MIT License (MIT)
